Sobol Sequence Generator/INT32_to_FP16.v
// transfer the INT32 value from Sobol to FP16
// modified FP16 scheme: 4 bits for exponent and 12 bits for mantissa (no sign bit since there are only positive values)
// exponent: the bit of the most significant one (be 11 if MSO <= 11)
// mantissa: counting 12 bits starting from exponent 
module INT32_to_FP16(
    input  [31:0] int32_val,
    output [15:0] fp16_val
);

// ========== parameters ==============
integer i;
// ========== wire and reg ============
wire  [3:0] exponent;
wire [11:0] mantissa;
// most significant one
reg   [4:0] MSO;

// ========== assignments =============
assign fp16_val = {exponent, mantissa};

assign exponent = MSO;
assign mantissa = int32_val[MSO -: 12];

// ========== Combinational ===========
always @(*) begin
    // MSO = 11;
    // for (i=12; i<32; i=i+1) begin
    //     if (int32_val[i] == 1) MSO = i;
    // end

    casex (int32_val)
        32'b1xxxxxxxxxxxxxxxxxxxxxxxxxxxxxxx: MSO = 5'd31;
        32'b01xxxxxxxxxxxxxxxxxxxxxxxxxxxxxx: MSO = 5'd30;
        32'b001xxxxxxxxxxxxxxxxxxxxxxxxxxxxx: MSO = 5'd29;
        32'b0001xxxxxxxxxxxxxxxxxxxxxxxxxxxx: MSO = 5'd28;
        32'b00001xxxxxxxxxxxxxxxxxxxxxxxxxxx: MSO = 5'd27;
        32'b000001xxxxxxxxxxxxxxxxxxxxxxxxxx: MSO = 5'd26;
        32'b0000001xxxxxxxxxxxxxxxxxxxxxxxxx: MSO = 5'd25;
        32'b00000001xxxxxxxxxxxxxxxxxxxxxxxx: MSO = 5'd24;
        32'b000000001xxxxxxxxxxxxxxxxxxxxxxx: MSO = 5'd23;
        32'b0000000001xxxxxxxxxxxxxxxxxxxxxx: MSO = 5'd22;
        32'b00000000001xxxxxxxxxxxxxxxxxxxxx: MSO = 5'd21;
        32'b000000000001xxxxxxxxxxxxxxxxxxxx: MSO = 5'd20;
        32'b00000000000001xxxxxxxxxxxxxxxxxx: MSO = 5'd19;
        32'b000000000000001xxxxxxxxxxxxxxxxx: MSO = 5'd18;
        32'b0000000000000001xxxxxxxxxxxxxxxx: MSO = 5'd17;
        32'b00000000000000001xxxxxxxxxxxxxxx: MSO = 5'd16;
        32'b000000000000000001xxxxxxxxxxxxxx: MSO = 5'd15;
        32'b0000000000000000001xxxxxxxxxxxxx: MSO = 5'd14;
        32'b00000000000000000001xxxxxxxxxxxx: MSO = 5'd13;
        32'b000000000000000000001xxxxxxxxxxx: MSO = 5'd12;
        default: MSO = 5'd11;
    endcase
end


endmodule

Sobol Sequence Generator/INT32_to_FP16_tb.v
`timescale 1ns/10ps
`define CYCLE 10.0

module INT32_to_FP16_tb;

// ============= clk generation ================
reg clk = 1;
always #(`CYCLE/2) clk = ~clk;


// ============= dump waveform =================
// fsdb
// initial begin
//     $fsdbDumpfile("INT32_to_FP16.fsdb");
//     $fsdbDumpvars(0, "+mda");
// end

// vcd
initial begin
    $dumpfile("INT32_to_FP16.vcd");
    $dumpvars(0, int32_to_fp16_0);
end

// time out
initial begin
    # (10000 * `CYCLE);
    $display("\n\033[1;31m=============================================");
	$display("           Simulation Time Out!      ");
	$display("=============================================\033[0m");
	$finish;
end

// instantiate DUT
reg  [31:0] int32_val = 0;
wire [15:0] fp16_val;

INT32_to_FP16 int32_to_fp16_0(
    .int32_val(int32_val),
    .fp16_val(fp16_val)
);

// input pattern
// integer i;

initial begin
    // update weight
    @(posedge clk) int32_val = 32'b00000011001100100000000000000000;
    @(posedge clk) int32_val = 32'b00000110110001000000000000000000;
    @(posedge clk) int32_val = 32'b00001101100010000000000000000000;
    @(posedge clk) int32_val = 32'b00011011110100000000000000000000;
    @(posedge clk) int32_val = 32'b00110111011000000000000000000000;
    @(posedge clk) int32_val = 32'b01101111010000000000000000000000;
    @(posedge clk) int32_val = 32'b00000000000000000000000000111100;
end

endmodule

Sobol Sequence Generator/INT32_to_FP16.vcd
$date
	Thu May 05 15:11:52 2022
$end
$version
	Icarus Verilog
$end
$timescale
	10ps
$end
$scope module INT32_to_FP16_tb $end
$scope module int32_to_fp16_0 $end
$var wire 32 ! int32_val [31:0] $end
$var wire 12 " mantissa [11:0] $end
$var wire 16 # fp16_val [15:0] $end
$var wire 4 $ exponent [3:0] $end
$var reg 5 % MSO [4:0] $end
$var integer 32 & i [31:0] $end
$upscope $end
$upscope $end
$enddefinitions $end
#0
$dumpvars
b100000 &
b1011 %
b1011 $
b1011000000000000 #
b0 "
b0 !
$end
#1000
b1001 $
b1001110011001000 #
b110011001000 "
b11001 %
b100000 &
b11001100100000000000000000 !
#2000
b1010 $
b100000 &
b11010 %
b1010110110001000 #
b110110001000 "
b110110001000000000000000000 !
#3000
b1011 $
b100000 &
b11011 %
b1011110110001000 #
b110110001000 "
b1101100010000000000000000000 !
#4000
b1100 $
b100000 &
b11100 %
b1100110111101000 #
b110111101000 "
b11011110100000000000000000000 !
#5000
b1101 $
b100000 &
b11101 %
b1101110111011000 #
b110111011000 "
b110111011000000000000000000000 !
#6000
b1110 $
b100000 &
b11110 %
b1110110111101000 #
b110111101000 "
b1101111010000000000000000000000 !
#7000
b1011 $
b100000 &
b1011 %
b1011000000111100 #
b111100 "
b111100 !
