Sobol Sequence Generator/ICDF_LUT.v
module ICDF_LUT(
    input               clk,
    input               rst_n,
    input       [31:0]  cdf,
    output reg  [15:0]  icdf
);
// =========== parameter ===============
parameter [16*64-1: 0] LUT = {
    16'ha103,
    16'ha785,
    16'haa45,
    16'hac64,
    16'hada6,
    16'haee8,
    16'hb016,
    16'hb0b8,
    16'hb15a,
    16'hb1fd,
    16'hb2a1,
    16'hb345,
    16'hb3ea,
    16'hb448,
    16'hb49b,
    16'hb4ef,
    16'hb543,
    16'hb598,
    16'hb5ee,
    16'hb644,
    16'hb69b,
    16'hb6f3,
    16'hb74c,
    16'hb7a5,
    16'hb7ff,
    16'hb82d,
    16'hb85c,
    16'hb88a,
    16'hb8ba,
    16'hb8ea,
    16'hb91b,
    16'hb94c,
    16'hb97f,
    16'hb9b2,
    16'hb9e6,
    16'hba1b,
    16'hba51,
    16'hba89,
    16'hbac1,
    16'hbafb,
    16'hbb37,
    16'hbb74,
    16'hbbb3,
    16'hbbf3,
    16'hbc1b,
    16'hbc3e,
    16'hbc61,
    16'hbc87,
    16'hbcae,
    16'hbcd6,
    16'hbd01,
    16'hbd2e,
    16'hbd5e,
    16'hbd91,
    16'hbdc8,
    16'hbe03,
    16'hbe44,
    16'hbe8d,
    16'hbede,
    16'hbf3d,
    16'hbfaf,
    16'hc021,
    16'hc088,
    16'hc152
};
// ================ wire and reg ==================
// whether cdf is greater than 0.5
wire GT05;
wire [5:0] index;
reg [16:0] icdf_w;
// ================ assignment ====================
assign GT05 = cdf[31];
assign index = cdf[30 -: 6];
// ================ Combinational =================
always@(*) begin
    if (!GT05) begin
        icdf_w = LUT[16*(index+1)-1 -: 16];    
    end
    else begin
        icdf_w = {1'b0, LUT[16*((63-index)+1)-2 -: 15]};
    end 
end
// ================ Sequential ====================
always @(posedge clk or negedge rst_n) begin
    if (!rst_n) icdf <= 16'b0;
    else        icdf <= icdf_w;
end

endmodule

src_final/Sobol_to_INT32.v
module Sobol_to_INT32(
    input             clk,
    input             rst_n, 
    input             start,
    output reg [31:0] res
);
// ================== parameter =========================
parameter IDLE = 1'b0;
parameter COMP = 1'b1;
// DVA31, DVA30 , ......, DVA1, DVA0
parameter [32*32-1:0] DVA = {
    32'b00000000000000000000000111110011,
    32'b00000000000000000000001100110010,
    32'b00000000000000000000011011000100,
    32'b00000000000000000000110110001000,
    32'b00000000000000000001101111010000,
    32'b00000000000000000011011101100000,
    32'b00000000000000000110111101000000,
    32'b00000000000000001101111110000000,
    32'b00000000000000000100110100000000,
    32'b00000000000000000100111000000000,
    32'b00000000000000000011110000000000,
    32'b00000000000000000111100000000000,
    32'b00000000000000000011000000000000,
    32'b00000000000000001010000000000000,
    32'b00000000000000001100000000000000,
    32'b00000000000000001000000000000000,
    32'b00000001111100110000000000000000,
    32'b00000011001100100000000000000000,
    32'b00000110110001000000000000000000,
    32'b00001101100010000000000000000000,
    32'b00011011110100000000000000000000,
    32'b00110111011000000000000000000000,
    32'b01101111010000000000000000000000,
    32'b11011111100000000000000000000000,
    32'b01001101000000000000000000000000,
    32'b01001110000000000000000000000000,
    32'b00111100000000000000000000000000,
    32'b01111000000000000000000000000000,
    32'b00110000000000000000000000000000,
    32'b10100000000000000000000000000000,
    32'b11000000000000000000000000000000,
    32'b10000000000000000000000000000000
};


// ================== reg and wire ======================
// reg   [31:0] res0, res1, res2, res3;
wire  [31:0] res_w;

reg          state, state_ns;

reg   [31:0] counter;
reg   [4:0] LSZ;

integer i;

// ================== wire assignments ==================
assign res_w = res ^ DVA[32*(LSZ+1)-1 -: 32];

// ================== Combinational =====================
// state
always @(*) begin
    state_ns = state;
    case (state_ns)
        IDLE: begin
            if (start) state_ns = COMP;
        end 
        COMP: begin
            
        end
        default: begin
            
        end
    endcase
end
// counter 
always @(*) begin

    // for (i=0; i < 32; i = i+1) begin
    //     if (counter[31 - i] == 0) LSZ = 31 - i;
    // end

    ///////LSZ is a latch, modified as below///////
    casex (counter)
        32'bxxxxxxxxxxxxxxxxxxxxxxxxxxxxxxx0: LSZ = 5'd0;
        32'bxxxxxxxxxxxxxxxxxxxxxxxxxxxxxx01: LSZ = 5'd1;
        32'bxxxxxxxxxxxxxxxxxxxxxxxxxxxxx011: LSZ = 5'd2;
        32'bxxxxxxxxxxxxxxxxxxxxxxxxxxxx0111: LSZ = 5'd3;
        32'bxxxxxxxxxxxxxxxxxxxxxxxxxxx01111: LSZ = 5'd4;
        32'bxxxxxxxxxxxxxxxxxxxxxxxxxx011111: LSZ = 5'd5;
        32'bxxxxxxxxxxxxxxxxxxxxxxxxx0111111: LSZ = 5'd6;
        32'bxxxxxxxxxxxxxxxxxxxxxxxx01111111: LSZ = 5'd7;
        32'bxxxxxxxxxxxxxxxxxxxxxxx011111111: LSZ = 5'd8;
        32'bxxxxxxxxxxxxxxxxxxxxxx0111111111: LSZ = 5'd9;
        32'bxxxxxxxxxxxxxxxxxxxxx01111111111: LSZ = 5'd10;
        32'bxxxxxxxxxxxxxxxxxxxx011111111111: LSZ = 5'd11;
        32'bxxxxxxxxxxxxxxxxxxx0111111111111: LSZ = 5'd12;
        32'bxxxxxxxxxxxxxxxxxx01111111111111: LSZ = 5'd13;
        32'bxxxxxxxxxxxxxxxxx011111111111111: LSZ = 5'd14;
        32'bxxxxxxxxxxxxxxxx0111111111111111: LSZ = 5'd15;
        32'bxxxxxxxxxxxxxxx01111111111111111: LSZ = 5'd16;
        32'bxxxxxxxxxxxxxx011111111111111111: LSZ = 5'd17;
        32'bxxxxxxxxxxxxx0111111111111111111: LSZ = 5'd18;
        32'bxxxxxxxxxxxx01111111111111111111: LSZ = 5'd19;
        32'bxxxxxxxxxxx011111111111111111111: LSZ = 5'd20;
        32'bxxxxxxxxxx0111111111111111111111: LSZ = 5'd21;
        32'bxxxxxxxxx01111111111111111111111: LSZ = 5'd22;
        32'bxxxxxxxx011111111111111111111111: LSZ = 5'd23;
        32'bxxxxxxx0111111111111111111111111: LSZ = 5'd24;
        32'bxxxxxx01111111111111111111111111: LSZ = 5'd25;
        32'bxxxxx011111111111111111111111111: LSZ = 5'd26;
        32'bxxxx0111111111111111111111111111: LSZ = 5'd27;
        32'bxxx01111111111111111111111111111: LSZ = 5'd28;
        32'bxx011111111111111111111111111111: LSZ = 5'd29;
        32'bx0111111111111111111111111111111: LSZ = 5'd30;
        32'b01111111111111111111111111111111: LSZ = 5'd31;
        default: LSZ = 5'd0;
    endcase 
end


// ================== sequential ========================
always @(posedge clk or negedge rst_n) begin
    if (!rst_n) begin
        res     <= 32'b0;
        counter <= 32'b0;
        state   <= IDLE;
    end
    else begin
        state <= state_ns;
        if (state == COMP) begin
            res     <= res_w;
            counter <= counter + 32'b1;
        end
        else begin
            res     <= 32'b0;
            counter <= 32'b0;
        end
    end
end

endmodule

Sobol Sequence Generator/Sobol.v
module Sobol(
    input             clk,
    input             rst_n,
    input             start,
    output     [15:0] icdf
);

// ========== wire and reg ===================
wire [31:0] res_int32;

// ========== Sequential =====================

// ========== module instantiation ===========
Sobol_to_INT32 sobol_to_int32_0(
    .clk(clk),
    .rst_n(rst_n),
    .start(start),
    .res(res_int32)
);

ICDF_LUT icdf_lut0(
    .clk(clk),
    .rst_n(rst_n),
    .cdf(res_int32),
    .icdf(icdf)
);

endmodule

Sobol Sequence Generator/Sobol_tb.v
`timescale 1ns/10ps
`define CYCLE 10.0

module Sobol_tb;

// ============= clk generation ================
reg clk = 1;
always #(`CYCLE/2) clk = ~clk;


// ============= dump waveform =================
// fsdb
// initial begin
//     $fsdbDumpfile("Sobol.fsdb");
//     $fsdbDumpvars(0, "+mda");
// end

// vcd
initial begin
    $dumpfile("Sobol.vcd");
    $dumpvars(0, sobol0);
end

// time out
initial begin
    # (10000 * `CYCLE);
    $display("\n\033[1;31m=============================================");
	$display("           Simulation Time Out!      ");
	$display("=============================================\033[0m");
	$finish;
end

// instantiate DUT
reg          rst_n = 1;
reg          start = 0;
wire [15:0]  icdf;

Sobol sobol0(
    .clk(clk),
    .rst_n(rst_n),
    .start(start),
    .icdf(icdf)
);

// input pattern
integer i;

initial begin
    // update weight
    @(posedge clk) rst_n = 0;
    @(posedge clk) rst_n = 1;
    for (i=0; i < 5; i=i+1) begin
        @(posedge clk);
    end
    start <= 1;
end

endmodule

Sobol Sequence Generator/Sobol.vcd
$date
	Thu May 12 10:54:07 2022
$end
$version
	Icarus Verilog
$end
$timescale
	10ps
$end
$scope module Sobol_tb $end
$scope module sobol0 $end
$var wire 1 ! clk $end
$var wire 1 " rst_n $end
$var wire 1 # start $end
$var wire 32 $ res_int32 [31:0] $end
$var wire 16 % icdf [15:0] $end
$scope module icdf_lut0 $end
$var wire 1 ! clk $end
$var wire 1 " rst_n $end
$var wire 6 & index [5:0] $end
$var wire 32 ' cdf [31:0] $end
$var wire 1 ( GT05 $end
$var reg 16 ) icdf [15:0] $end
$var reg 17 * icdf_w [16:0] $end
$upscope $end
$scope module sobol_to_int32_0 $end
$var wire 1 ! clk $end
$var wire 32 + res_w [31:0] $end
$var wire 1 " rst_n $end
$var wire 1 # start $end
$var reg 5 , LSZ [4:0] $end
$var reg 32 - counter [31:0] $end
$var reg 32 . res [31:0] $end
$var reg 1 / state $end
$var reg 1 0 state_ns $end
$upscope $end
$upscope $end
$upscope $end
$enddefinitions $end
#0
$dumpvars
x0
x/
b0 .
b0 -
b0 ,
b10000000000000000000000000000000 +
b1100000101010010 *
bx )
0(
b0 '
b0 &
bx %
b0 $
0#
1"
1!
$end
#500
0!
#1000
00
b0 %
b0 )
0/
0"
1!
#1500
0!
#2000
b1100000101010010 %
b1100000101010010 )
1"
1!
#2500
0!
#3000
1!
#3500
0!
#4000
1!
#4500
0!
#5000
1!
#5500
0!
#6000
1!
#6500
0!
#7000
10
1#
1!
#7500
0!
#8000
1/
1!
#8500
0!
#9000
b10000100000011 *
b1 ,
b1000000000000000000000000000000 +
1(
b1 -
b10000000000000000000000000000000 $
b10000000000000000000000000000000 '
b10000000000000000000000000000000 .
1!
#9500
0!
#10000
b1011100101001100 *
b0 ,
b11000000000000000000000000000000 +
b100000 &
0(
b10 -
b1000000000000000000000000000000 $
b1000000000000000000000000000000 '
b1000000000000000000000000000000 .
b10000100000011 %
b10000100000011 )
1!
#10500
0!
#11000
b11100101111111 *
b10 ,
b1100000000000000000000000000000 +
1(
b1011100101001100 %
b1011100101001100 )
b11 -
b11000000000000000000000000000000 $
b11000000000000000000000000000000 '
b11000000000000000000000000000000 .
1!
#11500
0!
#12000
b1011010011101111 *
b0 ,
b11100000000000000000000000000000 +
b110000 &
0(
b100 -
b1100000000000000000000000000000 $
b1100000000000000000000000000000 '
b1100000000000000000000000000000 .
b11100101111111 %
b11100101111111 )
1!
#12500
0!
#13000
b11110010101110 *
b1 ,
b100000000000000000000000000000 +
1(
b1011010011101111 %
b1011010011101111 )
b101 -
b11100000000000000000000000000000 $
b11100000000000000000000000000000 '
b11100000000000000000000000000000 .
1!
#13500
0!
#14000
b1011110010000111 *
b0 ,
b10100000000000000000000000000000 +
b10000 &
0(
b110 -
b100000000000000000000000000000 $
b100000000000000000000000000000 '
b100000000000000000000000000000 .
b11110010101110 %
b11110010101110 )
1!
#14500
0!
#15000
b11010101000011 *
b11 ,
b10010000000000000000000000000000 +
1(
b1011110010000111 %
b1011110010000111 )
b111 -
b10100000000000000000000000000000 $
b10100000000000000000000000000000 '
b10100000000000000000000000000000 .
1!
#15500
0!
#16000
b11000101011010 *
b0 ,
b10000000000000000000000000000 +
b1000 &
b1000 -
b10010000000000000000000000000000 $
b10010000000000000000000000000000 '
b10010000000000000000000000000000 .
b11010101000011 %
b11010101000011 )
1!
#16500
0!
#17000
b1011111000000011 *
b1 ,
b11010000000000000000000000000000 +
0(
b11000101011010 %
b11000101011010 )
b1001 -
b10000000000000000000000000000 $
b10000000000000000000000000000 '
b10000000000000000000000000000 .
1!
#17500
0!
#18000
b11101100110111 *
b0 ,
b1010000000000000000000000000000 +
b101000 &
1(
b1010 -
b11010000000000000000000000000000 $
b11010000000000000000000000000000 '
b11010000000000000000000000000000 .
b1011111000000011 %
b1011111000000011 )
1!
#18500
0!
#19000
b1011011110100101 *
b10 ,
b11110000000000000000000000000000 +
0(
b11101100110111 %
b11101100110111 )
b1011 -
b1010000000000000000000000000000 $
b1010000000000000000000000000000 '
b1010000000000000000000000000000 .
1!
#19500
0!
#20000
b11111001000100 *
b0 ,
b1110000000000000000000000000000 +
b111000 &
1(
b1100 -
b11110000000000000000000000000000 $
b11110000000000000000000000000000 '
b11110000000000000000000000000000 .
b1011011110100101 %
b1011011110100101 )
1!
#20500
0!
#21000
b1011000010111000 *
b1 ,
b10110000000000000000000000000000 +
0(
b11111001000100 %
b11111001000100 )
b1101 -
b1110000000000000000000000000000 $
b1110000000000000000000000000000 '
b1110000000000000000000000000000 .
1!
#21500
0!
#22000
b11011111111111 *
b0 ,
b110000000000000000000000000000 +
b11000 &
1(
b1110 -
b10110000000000000000000000000000 $
b10110000000000000000000000000000 '
b10110000000000000000000000000000 .
b1011000010111000 %
b1011000010111000 )
1!
#22500
0!
#23000
b1011101011111011 *
b100 ,
b1001000000000000000000000000000 +
0(
b11011111111111 %
b11011111111111 )
b1111 -
b110000000000000000000000000000 $
b110000000000000000000000000000 '
b110000000000000000000000000000 .
1!
#23500
0!
#24000
b1011100010001010 *
b0 ,
b11001000000000000000000000000000 +
b100100 &
b10000 -
b1001000000000000000000000000000 $
b1001000000000000000000000000000 '
b1001000000000000000000000000000 .
b1011101011111011 %
b1011101011111011 )
1!
#24500
0!
#25000
b11101001010001 *
b1 ,
b1000000000000000000000000000 +
1(
b1011100010001010 %
b1011100010001010 )
b10001 -
b11001000000000000000000000000000 $
b11001000000000000000000000000000 '
b11001000000000000000000000000000 .
1!
#25500
0!
#26000
b1011111100111101 *
b0 ,
b10001000000000000000000000000000 +
b100 &
0(
b10010 -
b1000000000000000000000000000 $
b1000000000000000000000000000 '
b1000000000000000000000000000 .
b11101001010001 %
b11101001010001 )
1!
#26500
0!
#27000
b10110110100110 *
b10 ,
b101000000000000000000000000000 +
1(
b1011111100111101 %
b1011111100111101 )
b10011 -
b10001000000000000000000000000000 $
b10001000000000000000000000000000 '
b10001000000000000000000000000000 .
1!
#27500
0!
#28000
b1011101111110011 *
b0 ,
b10101000000000000000000000000000 +
b10100 &
0(
b10100 -
b101000000000000000000000000000 $
b101000000000000000000000000000 '
b101000000000000000000000000000 .
b10110110100110 %
b10110110100110 )
1!
#28500
0!
#29000
b11011010011011 *
b1 ,
b1101000000000000000000000000000 +
1(
b1011101111110011 %
b1011101111110011 )
b10101 -
b10101000000000000000000000000000 $
b10101000000000000000000000000000 '
b10101000000000000000000000000000 .
1!
#29500
0!
#30000
b1011001101000101 *
b0 ,
b11101000000000000000000000000000 +
b110100 &
0(
b10110 -
b1101000000000000000000000000000 $
b1101000000000000000000000000000 '
b1101000000000000000000000000000 .
b11011010011011 %
b11011010011011 )
1!
#30500
0!
#31000
b11110101011110 *
b11 ,
b11011000000000000000000000000000 +
1(
b1011001101000101 %
b1011001101000101 )
b10111 -
b11101000000000000000000000000000 $
b11101000000000000000000000000000 '
b11101000000000000000000000000000 .
1!
#31500
0!
#32000
b11110000011011 *
b0 ,
b1011000000000000000000000000000 +
b101100 &
b11000 -
b11011000000000000000000000000000 $
b11011000000000000000000000000000 '
b11011000000000000000000000000000 .
b11110101011110 %
b11110101011110 )
1!
#32500
0!
#33000
b1011011001000100 *
b1 ,
b10011000000000000000000000000000 +
0(
b11110000011011 %
b11110000011011 )
b11001 -
b1011000000000000000000000000000 $
b1011000000000000000000000000000 '
b1011000000000000000000000000000 .
1!
#33500
0!
#34000
b11001111101010 *
b0 ,
b11000000000000000000000000000 +
b1100 &
1(
b11010 -
b10011000000000000000000000000000 $
b10011000000000000000000000000000 '
b10011000000000000000000000000000 .
b1011011001000100 %
b1011011001000100 )
1!
#34500
0!
#35000
b1011110100101110 *
b10 ,
b10111000000000000000000000000000 +
0(
b11001111101010 %
b11001111101010 )
b11011 -
b11000000000000000000000000000 $
b11000000000000000000000000000 '
b11000000000000000000000000000 .
1!
#35500
0!
#36000
b11100010111010 *
b0 ,
b111000000000000000000000000000 +
b11100 &
1(
b11100 -
b10111000000000000000000000000000 $
b10111000000000000000000000000000 '
b10111000000000000000000000000000 .
b1011110100101110 %
b1011110100101110 )
1!
#36500
0!
#37000
b1011101000011011 *
b1 ,
b11111000000000000000000000000000 +
0(
b11100010111010 %
b11100010111010 )
b11101 -
b111000000000000000000000000000 $
b111000000000000000000000000000 '
b111000000000000000000000000000 .
1!
#37500
0!
#38000
b11111110101111 *
b0 ,
b1111000000000000000000000000000 +
b111100 &
1(
b11110 -
b11111000000000000000000000000000 $
b11111000000000000000000000000000 '
b11111000000000000000000000000000 .
b1011101000011011 %
b1011101000011011 )
1!
#38500
0!
#39000
b1010110001100100 *
b101 ,
b1000100000000000000000000000000 +
0(
b11111110101111 %
b11111110101111 )
b11111 -
b1111000000000000000000000000000 $
b1111000000000000000000000000000 '
b1111000000000000000000000000000 .
1!
#39500
0!
#40000
b1011100011101010 *
b0 ,
b11000100000000000000000000000000 +
b100010 &
b100000 -
b1000100000000000000000000000000 $
b1000100000000000000000000000000 '
b1000100000000000000000000000000 .
b1010110001100100 %
b1010110001100100 )
1!
#40500
0!
#41000
b11100111100110 *
b1 ,
b100000000000000000000000000 +
1(
b1011100011101010 %
b1011100011101010 )
b100001 -
b11000100000000000000000000000000 $
b11000100000000000000000000000000 '
b11000100000000000000000000000000 .
1!
#41500
0!
#42000
b1100000000100001 *
b0 ,
b10000100000000000000000000000000 +
b10 &
0(
b100010 -
b100000000000000000000000000 $
b100000000000000000000000000 '
b100000000000000000000000000 .
b11100111100110 %
b11100111100110 )
1!
#42500
0!
#43000
b10101001000101 *
b10 ,
b100100000000000000000000000000 +
1(
b1100000000100001 %
b1100000000100001 )
b100011 -
b10000100000000000000000000000000 $
b10000100000000000000000000000000 '
b10000100000000000000000000000000 .
1!
#43500
0!
#44000
b1011110000111110 *
b0 ,
b10100100000000000000000000000000 +
b10010 &
0(
b100100 -
b100100000000000000000000000000 $
b100100000000000000000000000000 '
b100100000000000000000000000000 .
b10101001000101 %
b10101001000101 )
1!
#44500
0!
#45000
b11010111101110 *
b1 ,
b1100100000000000000000000000000 +
1(
b1011110000111110 %
b1011110000111110 )
b100101 -
b10100100000000000000000000000000 $
b10100100000000000000000000000000 '
b10100100000000000000000000000000 .
1!
#45500
0!
#46000
b1011010001001000 *
b0 ,
b11100100000000000000000000000000 +
b110010 &
0(
b100110 -
b1100100000000000000000000000000 $
b1100100000000000000000000000000 '
b1100100000000000000000000000000 .
b11010111101110 %
b11010111101110 )
1!
#46500
0!
#47000
b11110100000001 *
b11 ,
b11010100000000000000000000000000 +
1(
b1011010001001000 %
b1011010001001000 )
b100111 -
b11100100000000000000000000000000 $
b11100100000000000000000000000000 '
b11100100000000000000000000000000 .
1!
#47500
0!
#48000
b11101110110011 *
b0 ,
b1010100000000000000000000000000 +
b101010 &
b101000 -
b11010100000000000000000000000000 $
b11010100000000000000000000000000 '
b11010100000000000000000000000000 .
b11110100000001 %
b11110100000001 )
1!
#48500
0!
#49000
b1011011011110011 *
b1 ,
b10010100000000000000000000000000 +
0(
b11101110110011 %
b11101110110011 )
b101001 -
b1010100000000000000000000000000 $
b1010100000000000000000000000000 '
b1010100000000000000000000000000 .
1!
#49500
0!
#50000
b11001010100001 *
b0 ,
b10100000000000000000000000000 +
b1010 &
1(
b101010 -
b10010100000000000000000000000000 $
b10010100000000000000000000000000 '
b10010100000000000000000000000000 .
b1011011011110011 %
b1011011011110011 )
1!
#50500
0!
#51000
b1011110110010001 *
b10 ,
b10110100000000000000000000000000 +
0(
b11001010100001 %
b11001010100001 )
b101011 -
b10100000000000000000000000000 $
b10100000000000000000000000000 '
b10100000000000000000000000000 .
1!
#51500
0!
#52000
b11100001011100 *
b0 ,
b110100000000000000000000000000 +
b11010 &
1(
b101100 -
b10110100000000000000000000000000 $
b10110100000000000000000000000000 '
b10110100000000000000000000000000 .
b1011110110010001 %
b1011110110010001 )
1!
#52500
0!
#53000
b1011101010001001 *
b1 ,
b11110100000000000000000000000000 +
0(
b11100001011100 %
b11100001011100 )
b101101 -
b110100000000000000000000000000 $
b110100000000000000000000000000 '
b110100000000000000000000000000 .
1!
#53500
0!
#54000
b11111011011110 *
b0 ,
b1110100000000000000000000000000 +
b111010 &
1(
b101110 -
b11110100000000000000000000000000 $
b11110100000000000000000000000000 '
b11110100000000000000000000000000 .
b1011101010001001 %
b1011101010001001 )
1!
#54500
0!
#55000
b1010111011101000 *
b100 ,
b1100000000000000000000000000 +
0(
b11111011011110 %
b11111011011110 )
b101111 -
b1110100000000000000000000000000 $
b1110100000000000000000000000000 '
b1110100000000000000000000000000 .
1!
#55500
0!
#56000
b1011111010001101 *
b0 ,
b10001100000000000000000000000000 +
b110 &
b110000 -
b1100000000000000000000000000 $
b1100000000000000000000000000 '
b1100000000000000000000000000 .
b1010111011101000 %
b1010111011101000 )
1!
#56500
0!
#57000
b11000000010110 *
b1 ,
b1001100000000000000000000000000 +
1(
b1011111010001101 %
b1011111010001101 )
b110001 -
b10001100000000000000000000000000 $
b10001100000000000000000000000000 '
b10001100000000000000000000000000 .
1!
#57500
0!
#58000
b1011100000101101 *
b0 ,
b11001100000000000000000000000000 +
b100110 &
0(
b110010 -
b1001100000000000000000000000000 $
b1001100000000000000000000000000 '
b1001100000000000000000000000000 .
b11000000010110 %
b11000000010110 )
1!
#58500
0!
#59000
b11101011000001 *
b10 ,
b1101100000000000000000000000000 +
1(
b1011100000101101 %
b1011100000101101 )
b110011 -
b11001100000000000000000000000000 $
b11001100000000000000000000000000 '
b11001100000000000000000000000000 .
1!
#59500
0!
#60000
b1011000111111101 *
b0 ,
b11101100000000000000000000000000 +
b110110 &
0(
b110100 -
b1101100000000000000000000000000 $
b1101100000000000000000000000000 '
b1101100000000000000000000000000 .
b11101011000001 %
b11101011000001 )
1!
#60500
0!
#61000
b11110111001000 *
b1 ,
b101100000000000000000000000000 +
1(
b1011000111111101 %
b1011000111111101 )
b110101 -
b11101100000000000000000000000000 $
b11101100000000000000000000000000 '
b11101100000000000000000000000000 .
1!
#61500
0!
#62000
b1011101101110100 *
b0 ,
b10101100000000000000000000000000 +
b10110 &
0(
b110110 -
b101100000000000000000000000000 $
b101100000000000000000000000000 '
b101100000000000000000000000000 .
b11110111001000 %
b11110111001000 )
1!
#62500
0!
#63000
b11011101001100 *
b11 ,
b10011100000000000000000000000000 +
1(
b1011101101110100 %
b1011101101110100 )
b110111 -
b10101100000000000000000000000000 $
b10101100000000000000000000000000 '
b10101100000000000000000000000000 .
1!
#63500
0!
#64000
b11010010011011 *
b0 ,
b11100000000000000000000000000 +
b1110 &
b111000 -
b10011100000000000000000000000000 $
b10011100000000000000000000000000 '
b10011100000000000000000000000000 .
b11011101001100 %
b11011101001100 )
1!
#64500
0!
#65000
b1011110011010110 *
b1 ,
b11011100000000000000000000000000 +
0(
b11010010011011 %
b11010010011011 )
b111001 -
b11100000000000000000000000000 $
b11100000000000000000000000000 '
b11100000000000000000000000000 .
1!
#65500
0!
#66000
b11110001100001 *
b0 ,
b1011100000000000000000000000000 +
b101110 &
1(
b111010 -
b11011100000000000000000000000000 $
b11011100000000000000000000000000 '
b11011100000000000000000000000000 .
b1011110011010110 %
b1011110011010110 )
1!
#66500
0!
#67000
b1011010110011000 *
b10 ,
b11111100000000000000000000000000 +
0(
b11110001100001 %
b11110001100001 )
b111011 -
b1011100000000000000000000000000 $
b1011100000000000000000000000000 '
b1011100000000000000000000000000 .
1!
#67500
0!
#68000
b100000010001000 *
b0 ,
b1111100000000000000000000000000 +
b111110 &
1(
b111100 -
b11111100000000000000000000000000 $
b11111100000000000000000000000000 '
b11111100000000000000000000000000 .
b1011010110011000 %
b1011010110011000 )
1!
#68500
0!
#69000
b1010011110000101 *
b1 ,
b10111100000000000000000000000000 +
0(
b100000010001000 %
b100000010001000 )
b111101 -
b1111100000000000000000000000000 $
b1111100000000000000000000000000 '
b1111100000000000000000000000000 .
1!
#69500
0!
#70000
b11100100011011 *
b0 ,
b111100000000000000000000000000 +
b11110 &
1(
b111110 -
b10111100000000000000000000000000 $
b10111100000000000000000000000000 '
b10111100000000000000000000000000 .
b1010011110000101 %
b1010011110000101 )
1!
#70500
0!
#71000
b1011100110110010 *
b110 ,
b1110010000000000000000000000000 +
0(
b11100100011011 %
b11100100011011 )
b111111 -
b111100000000000000000000000000 $
b111100000000000000000000000000 '
b111100000000000000000000000000 .
1!
#71500
0!
#72000
b1011000000010110 *
b0 ,
b11110010000000000000000000000000 +
b111001 &
b1000000 -
b1110010000000000000000000000000 $
b1110010000000000000000000000000 '
b1110010000000000000000000000000 .
b1011100110110010 %
b1011100110110010 )
1!
#72500
0!
#73000
b11111010001101 *
b1 ,
b110010000000000000000000000000 +
1(
b1011000000010110 %
b1011000000010110 )
b1000001 -
b11110010000000000000000000000000 $
b11110010000000000000000000000000 '
b11110010000000000000000000000000 .
1!
#73500
0!
#74000
b1011101011000001 *
b0 ,
b10110010000000000000000000000000 +
b11001 &
0(
b1000010 -
b110010000000000000000000000000 $
b110010000000000000000000000000 '
b110010000000000000000000000000 .
b11111010001101 %
b11111010001101 )
1!
#74500
0!
#75000
b11100000101101 *
b10 ,
b10010000000000000000000000000 +
1(
b1011101011000001 %
b1011101011000001 )
b1000011 -
b10110010000000000000000000000000 $
b10110010000000000000000000000000 '
b10110010000000000000000000000000 .
1!
#75500
0!
#76000
b1011110111001000 *
b0 ,
b10010010000000000000000000000000 +
b1001 &
0(
b1000100 -
b10010000000000000000000000000 $
b10010000000000000000000000000 '
b10010000000000000000000000000 .
b11100000101101 %
b11100000101101 )
1!
#76500
0!
#77000
b11000111111101 *
b1 ,
b1010010000000000000000000000000 +
1(
b1011110111001000 %
b1011110111001000 )
b1000101 -
b10010010000000000000000000000000 $
b10010010000000000000000000000000 '
b10010010000000000000000000000000 .
1!
#77500
0!
#78000
b1011011101001100 *
b0 ,
b11010010000000000000000000000000 +
b101001 &
0(
b1000110 -
b1010010000000000000000000000000 $
b1010010000000000000000000000000 '
b1010010000000000000000000000000 .
b11000111111101 %
b11000111111101 )
1!
#78500
0!
#79000
b11101101110100 *
b11 ,
b11100010000000000000000000000000 +
1(
b1011011101001100 %
b1011011101001100 )
b1000111 -
b11010010000000000000000000000000 $
b11010010000000000000000000000000 '
b11010010000000000000000000000000 .
1!
#79500
0!
#80000
b11110011010110 *
b0 ,
b1100010000000000000000000000000 +
b110001 &
b1001000 -
b11100010000000000000000000000000 $
b11100010000000000000000000000000 '
b11100010000000000000000000000000 .
b11101101110100 %
b11101101110100 )
1!
#80500
0!
#81000
b1011010010011011 *
b1 ,
b10100010000000000000000000000000 +
0(
b11110011010110 %
b11110011010110 )
b1001001 -
b1100010000000000000000000000000 $
b1100010000000000000000000000000 '
b1100010000000000000000000000000 .
1!
#81500
0!
#82000
b11010110011000 *
b0 ,
b100010000000000000000000000000 +
b10001 &
1(
b1001010 -
b10100010000000000000000000000000 $
b10100010000000000000000000000000 '
b10100010000000000000000000000000 .
b1011010010011011 %
b1011010010011011 )
1!
#82500
0!
#83000
b1011110001100001 *
b10 ,
b10000010000000000000000000000000 +
0(
b11010110011000 %
b11010110011000 )
b1001011 -
b100010000000000000000000000000 $
b100010000000000000000000000000 '
b100010000000000000000000000000 .
1!
#83500
0!
#84000
b10011110000101 *
b0 ,
b10000000000000000000000000 +
b1 &
1(
b1001100 -
b10000010000000000000000000000000 $
b10000010000000000000000000000000 '
b10000010000000000000000000000000 .
b1011110001100001 %
b1011110001100001 )
1!
#84500
0!
#85000
b1100000010001000 *
b1 ,
b11000010000000000000000000000000 +
0(
b10011110000101 %
b10011110000101 )
b1001101 -
b10000000000000000000000000 $
b10000000000000000000000000 '
b10000000000000000000000000 .
1!
#85500
0!
#86000
b11100110110010 *
b0 ,
b1000010000000000000000000000000 +
b100001 &
1(
b1001110 -
b11000010000000000000000000000000 $
b11000010000000000000000000000000 '
b11000010000000000000000000000000 .
b1100000010001000 %
b1100000010001000 )
1!
#86500
0!
#87000
b1011100100011011 *
b100 ,
b111010000000000000000000000000 +
0(
b11100110110010 %
b11100110110010 )
b1001111 -
b1000010000000000000000000000000 $
b1000010000000000000000000000000 '
b1000010000000000000000000000000 .
1!
#87500
0!
#88000
b1011100111100110 *
b0 ,
b10111010000000000000000000000000 +
b11101 &
b1010000 -
b111010000000000000000000000000 $
b111010000000000000000000000000 '
b111010000000000000000000000000 .
b1011100100011011 %
b1011100100011011 )
1!
#88500
0!
#89000
b11100011101010 *
b1 ,
b1111010000000000000000000000000 +
1(
b1011100111100110 %
b1011100111100110 )
b1010001 -
b10111010000000000000000000000000 $
b10111010000000000000000000000000 '
b10111010000000000000000000000000 .
1!
#89500
0!
#90000
b1010101001000101 *
b0 ,
b11111010000000000000000000000000 +
b111101 &
0(
b1010010 -
b1111010000000000000000000000000 $
b1111010000000000000000000000000 '
b1111010000000000000000000000000 .
b11100011101010 %
b11100011101010 )
1!
#90500
0!
#91000
b100000000100001 *
b10 ,
b1011010000000000000000000000000 +
1(
b1010101001000101 %
b1010101001000101 )
b1010011 -
b11111010000000000000000000000000 $
b11111010000000000000000000000000 '
b11111010000000000000000000000000 .
1!
#91500
0!
#92000
b1011010111101110 *
b0 ,
b11011010000000000000000000000000 +
b101101 &
0(
b1010100 -
b1011010000000000000000000000000 $
b1011010000000000000000000000000 '
b1011010000000000000000000000000 .
b100000000100001 %
b100000000100001 )
1!
#92500
0!
